jsbsim/GeographicLib-LICENSE.txt
jsbsim/LICENSE.txt
jsbsim/__init__.py
jsbsim/_jsbsim.cpython-310-i386-linux-gnu.so
jsbsim/_jsbsim.pxd
jsbsim/_jsbsim.pyi
jsbsim/libexpat-LICENSE.txt
jsbsim/py.typed
jsbsim/aircraft/aircraft_template.xml
jsbsim/aircraft/737/737.xml
jsbsim/aircraft/737/cruise_init.xml
jsbsim/aircraft/737/cruise_steady_turn_init.xml
jsbsim/aircraft/737/reset00.xml
jsbsim/aircraft/737/rudder_kick_init.xml
jsbsim/aircraft/787-8/787-8.xml
jsbsim/aircraft/A320/A320.xml
jsbsim/aircraft/A4/A4.xml
jsbsim/aircraft/B17/B17.xml
jsbsim/aircraft/B17/reset00.xml
jsbsim/aircraft/B747/B747.xml
jsbsim/aircraft/B747/reset00.xml
jsbsim/aircraft/Boeing314/Boeing314.xml
jsbsim/aircraft/C130/C130.xml
jsbsim/aircraft/C130/reset00.xml
jsbsim/aircraft/Camel/sopwithCamel1F1jsb.xml
jsbsim/aircraft/Camel/Systems/automixture.xml
jsbsim/aircraft/Camel/Systems/crash-detect.xml
jsbsim/aircraft/Concorde/Concorde.xml
jsbsim/aircraft/Concorde/reset00.xml
jsbsim/aircraft/DHC6/DHC6.xml
jsbsim/aircraft/DHC6/Engines/PT6A-27.xml
jsbsim/aircraft/DHC6/Engines/Propeller.xml
jsbsim/aircraft/DHC6/Systems/Conventional Controls.xml
jsbsim/aircraft/DHC6/Systems/Flaps.xml
jsbsim/aircraft/DHC6/Systems/Landing Gear.xml
jsbsim/aircraft/DHC6/Systems/Propulsion.xml
jsbsim/aircraft/F450/Aero.xml
jsbsim/aircraft/F450/Effectors.xml
jsbsim/aircraft/F450/F450.xml
jsbsim/aircraft/F450/FlightControl.xml
jsbsim/aircraft/F450/Gear.xml
jsbsim/aircraft/F450/Mass.xml
jsbsim/aircraft/F450/Metrics.xml
jsbsim/aircraft/F450/Propulsion.xml
jsbsim/aircraft/F450/initGrnd.xml
jsbsim/aircraft/F4N/F4N-jsbsim.xml
jsbsim/aircraft/F4N/F4N.xml
jsbsim/aircraft/F4N/reset00.xml
jsbsim/aircraft/F4N/Engines/J79-GE-11A.xml
jsbsim/aircraft/F4N/Engines/direct.xml
jsbsim/aircraft/F80C/F80C.xml
jsbsim/aircraft/J246/J246.xml
jsbsim/aircraft/J246/LC39.xml
jsbsim/aircraft/J246/Systems/J246ControlSystem.xml
jsbsim/aircraft/J246/Systems/J246FirstStageEffectors.xml
jsbsim-1.2.3.dist-info/METADATA
jsbsim-1.2.3.dist-info/WHEEL
jsbsim-1.2.3.dist-info/top_level.txt
jsbsim-1.2.3.dist-info/RECORD
